simple_openid_connect/__init__.py
simple_openid_connect/base_data.py
simple_openid_connect/client.py
simple_openid_connect/client_authentication.py
simple_openid_connect/data.py
simple_openid_connect/discovery.py
simple_openid_connect/exceptions.py
simple_openid_connect/jwk.py
simple_openid_connect/pkce.py
simple_openid_connect/py.typed
simple_openid_connect/rp_initiated_logout.py
simple_openid_connect/token_introspection.py
simple_openid_connect/token_refresh.py
simple_openid_connect/userinfo.py
simple_openid_connect/utils.py
simple_openid_connect/flows/__init__.py
simple_openid_connect/flows/authorization_code_flow/__init__.py
simple_openid_connect/flows/authorization_code_flow/client.py
simple_openid_connect/flows/client_credentials_grant/__init__.py
simple_openid_connect/flows/client_credentials_grant/client.py
simple_openid_connect/flows/direct_access_grant/__init__.py
simple_openid_connect/flows/direct_access_grant/client.py
simple_openid_connect/integrations/__init__.py
simple_openid_connect/integrations/django/__init__.py
simple_openid_connect/integrations/django/admin.py
simple_openid_connect/integrations/django/apps.py
simple_openid_connect/integrations/django/decorators.py
simple_openid_connect/integrations/django/middleware.py
simple_openid_connect/integrations/django/models.py
simple_openid_connect/integrations/django/urls.py
simple_openid_connect/integrations/django/user_mapping.py
simple_openid_connect/integrations/django/views.py
simple_openid_connect/integrations/django/management/__init__.py
simple_openid_connect/integrations/django/management/commands/__init__.py
simple_openid_connect/integrations/django/management/commands/clear-expired-openid-sessions.py
simple_openid_connect/integrations/django/migrations/0001_initial.py
simple_openid_connect/integrations/django/migrations/0002_move_sessions_id_token.py
simple_openid_connect/integrations/django/migrations/0003_openidsession_add_raw_id_token.py
simple_openid_connect-2.3.2.dist-info/entry_points.txt
simple_openid_connect-2.3.2.dist-info/licenses/LICENSE
simple_openid_connect-2.3.2.dist-info/WHEEL
simple_openid_connect-2.3.2.dist-info/METADATA
simple_openid_connect-2.3.2.dist-info/RECORD
