Metadata-Version: 2.4
Name: simple_openid_connect
Version: 2.3.2
Summary: Simple and opinionated OpenID-Connect relying party and resource server implementation
Author-email: lilly <li@lly.sh>
Requires-Python: ~=3.9
Classifier: License :: OSI Approved :: MIT License
Classifier: Development Status :: 5 - Production/Stable
Classifier: Environment :: Other Environment
Classifier: Environment :: Web Environment
Classifier: Framework :: Django
Classifier: Intended Audience :: Developers
Classifier: Topic :: Internet
Classifier: Topic :: Internet :: WWW/HTTP
Classifier: Topic :: Internet :: WWW/HTTP :: HTTP Servers
Classifier: Topic :: Internet :: WWW/HTTP :: Session
Classifier: Topic :: Security
Classifier: Topic :: Utilities
License-File: LICENSE
Requires-Dist: cryptojwt~=1.8
Requires-Dist: furl~=2.1
Requires-Dist: pydantic~=2.6
Requires-Dist: requests~=2.31
Requires-Dist: django>=4.2 ; extra == "django"
Requires-Dist: djangorestframework~=3.14 ; extra == "djangorestframework"
Project-URL: Changelog, https://github.com/fsinfuhh/py_simple_openid_connect/blob/main/CHANGELOG.md
Project-URL: Documentation, https://simple-openid-connect.readthedocs.io/en/stable/
Project-URL: Home, https://github.com/fsinfuhh/py_simple_openid_connect
Project-URL: Source, https://github.com/fsinfuhh/py_simple_openid_connect
Provides-Extra: django
Provides-Extra: djangorestframework
